src/__init__.py
src/configuration/__init__.py
src/configuration/config.py
src/indexing/__init__.py
src/indexing/index.py
src/model_face_detection/__init__.py
src/model_face_detection/face_model.py
src/model_face_detection/filter_step_2.py
src/model_index_info/__init__.py
face_recognition_pkg-0.1.1.dist-info/METADATA
face_recognition_pkg-0.1.1.dist-info/WHEEL
face_recognition_pkg-0.1.1.dist-info/top_level.txt
face_recognition_pkg-0.1.1.dist-info/RECORD
