Metadata-Version: 2.2
Name: face_recognition_pkg
Version: 0.1.1
Summary: A package for face recognition in images and videos
Home-page: https://github.com/Anurich/face_recognition_package.git
Author: Your Name
Author-email: your.email@example.com
Classifier: Programming Language :: Python :: 3
Classifier: License :: OSI Approved :: MIT License
Classifier: Operating System :: OS Independent
Requires-Python: >=3.6
Requires-Dist: numpy
Requires-Dist: opencv-python
Requires-Dist: Pillow
Requires-Dist: sentence-transformers
Requires-Dist: ultralytics
Requires-Dist: supervision
Provides-Extra: cpu
Requires-Dist: faiss-cpu; extra == "cpu"
Provides-Extra: gpu
Requires-Dist: faiss-gpu; extra == "gpu"
Dynamic: author
Dynamic: author-email
Dynamic: classifier
Dynamic: description
Dynamic: description-content-type
Dynamic: home-page
Dynamic: provides-extra
Dynamic: requires-dist
Dynamic: requires-python
Dynamic: summary
